{
  "$ref": "http://core.espnuk.org/v2/sports/cricket/athletes/1204631",
  "id": "1204631",
  "guid": "9eb5457f-d7a8-3014-9afd-a2d63f61f436",
  "uid": "s:200~a:1204631",
  "type": "cricket",
  "name": "Najjam Shahzad",
  "firstName": "Najjam",
  "middleName": "",
  "lastName": "Shahzad",
  "shortName": "",
  "fullName": "Najjam Shahzad",
  "displayName": "Najjam Shahzad",
  "weight": 0,
  "height": 0.0,
  "age": 38,
  "dateOfBirthStr": "1988-03-05T00:00Z",
  "dateOfBirth": "1988-03-05T00:00Z",
  "dateOfDeathStr": "",
  "dateOfDeath": "",
  "isActive": true,
  "active": true,
  "gender": "M",
  "debutYear": null,
  "birthPlace": {},
  "jersey": null,
  "style": [],
  "styles": [],
  "position": {
    "$ref": "http://core.espnuk.org/v2/sports/cricket/positions/UKN",
    "id": "UKN",
    "name": "Unknown",
    "abbreviation": "UKN",
    "leaf": true,
    "parent": {
      "$ref": "http://core.espnuk.org/v2/sports/cricket/positions/UKN"
    }
  },
  "battingName": "Najjam Shahzad",
  "fieldingName": "Najjam Shahzad",
  "country": 134,
  "relations": [],
  "majorTeams": [
    {
      "$ref": "http://core.espnuk.org/v2/sports/cricket/teams/134"
    }
  ],
  "headshot": {
    "href": "https://a.espncdn.com/i/headshots/cricket/players/default-player-logo-500.png",
    "rel": [
      "full",
      "default"
    ]
  },
  "flag": {
    "href": "https://a.espncdn.com/i/teamlogos/cricket/500/134.png",
    "width": 500,
    "height": 500,
    "alt": "POR",
    "rel": [
      "full",
      "default"
    ]
  },
  "team": {
    "$ref": "http://core.espnuk.org/v2/sports/cricket/teams/134"
  },
  "news": {
    "$ref": "http://core.espnuk.org/v2/sports/cricket/athletes/1204631/news"
  },
  "debuts": [
    {
      "$ref": "http://core.espnuk.org/v2/sports/cricket/leagues/1201664/events/1201668"
    },
    {
      "$ref": "http://core.espnuk.org/v2/sports/cricket/leagues/1201665/events/1201668"
    },
    {
      "$ref": "http://core.espnuk.org/v2/sports/cricket/leagues/1201664/events/1201668"
    },
    {
      "$ref": "http://core.espnuk.org/v2/sports/cricket/leagues/1201665/events/1201668"
    }
  ],
  "links": [
    {
      "language": "en",
      "rel": [
        "playercard",
        "desktop"
      ],
      "href": "https://www.espncricinfo.com/ci/content/player/1204631.html",
      "text": "Player Card",
      "shortText": "Player Card",
      "isExternal": false,
      "isPremium": false
    }
  ]
}