{
  "$ref": "http://core.espnuk.org/v2/sports/cricket/athletes/1280678",
  "id": "1280678",
  "guid": "f626698d-d8cb-3922-94a9-5d93ac1cab2c",
  "uid": "s:200~a:1280678",
  "type": "cricket",
  "name": "Laksh Bakrania",
  "firstName": "Laksh",
  "middleName": "",
  "lastName": "Bakrania",
  "shortName": "Barkania",
  "fullName": "Laksh Snehal Bakrania",
  "displayName": "Laksh Bakrania",
  "weight": 0,
  "height": 0.0,
  "age": 18,
  "dateOfBirthStr": "2007-09-29T00:00Z",
  "dateOfBirth": "2007-09-29T00:00Z",
  "dateOfDeathStr": "",
  "dateOfDeath": "",
  "isActive": true,
  "active": true,
  "gender": "M",
  "debutYear": null,
  "birthPlace": {},
  "jersey": null,
  "style": [
    {
      "description": "Left-hand bat",
      "shortDescription": "Lhb",
      "type": "batting"
    },
    {
      "description": "Slow left-arm orthodox",
      "shortDescription": "Sla",
      "type": "bowling"
    }
  ],
  "styles": [
    {
      "description": "Left-hand bat",
      "shortDescription": "Lhb",
      "type": "batting"
    },
    {
      "description": "Slow left-arm orthodox",
      "shortDescription": "Sla",
      "type": "bowling"
    }
  ],
  "position": {
    "$ref": "http://core.espnuk.org/v2/sports/cricket/positions/AR",
    "id": "AR",
    "name": "Allrounder",
    "abbreviation": "AR",
    "leaf": true,
    "parent": {
      "$ref": "http://core.espnuk.org/v2/sports/cricket/positions/AR"
    }
  },
  "battingName": "LS Barkania",
  "fieldingName": "Barkania",
  "country": 160,
  "relations": [],
  "majorTeams": [
    {
      "$ref": "http://core.espnuk.org/v2/sports/cricket/teams/160"
    },
    {
      "$ref": "http://core.espnuk.org/v2/sports/cricket/teams/297287"
    }
  ],
  "headshot": {
    "href": "https://a.espncdn.com/i/headshots/cricket/players/default-player-logo-500.png",
    "rel": [
      "full",
      "default"
    ]
  },
  "flag": {
    "href": "https://a.espncdn.com/i/teamlogos/cricket/500/160.png",
    "width": 500,
    "height": 500,
    "alt": "TAN",
    "rel": [
      "full",
      "default"
    ]
  },
  "team": {
    "$ref": "http://core.espnuk.org/v2/sports/cricket/teams/160"
  },
  "news": {
    "$ref": "http://core.espnuk.org/v2/sports/cricket/athletes/1280678/news"
  },
  "debuts": [
    {
      "$ref": "http://core.espnuk.org/v2/sports/cricket/leagues/1450709/events/1450753"
    },
    {
      "$ref": "http://core.espnuk.org/v2/sports/cricket/leagues/1450714/events/1450753"
    },
    {
      "$ref": "http://core.espnuk.org/v2/sports/cricket/leagues/1420563/events/1420571"
    },
    {
      "$ref": "http://core.espnuk.org/v2/sports/cricket/leagues/1420567/events/1420571"
    },
    {
      "$ref": "http://core.espnuk.org/v2/sports/cricket/leagues/1420549/events/1420571"
    },
    {
      "$ref": "http://core.espnuk.org/v2/sports/cricket/leagues/1450709/events/1450753"
    },
    {
      "$ref": "http://core.espnuk.org/v2/sports/cricket/leagues/1450714/events/1450753"
    },
    {
      "$ref": "http://core.espnuk.org/v2/sports/cricket/leagues/1519011/events/1511852"
    },
    {
      "$ref": "http://core.espnuk.org/v2/sports/cricket/leagues/1519010/events/1511852"
    },
    {
      "$ref": "http://core.espnuk.org/v2/sports/cricket/leagues/1511849/events/1511852"
    }
  ],
  "links": [
    {
      "language": "en",
      "rel": [
        "playercard",
        "desktop"
      ],
      "href": "https://www.espncricinfo.com/ci/content/player/1280678.html",
      "text": "Player Card",
      "shortText": "Player Card",
      "isExternal": false,
      "isPremium": false
    }
  ]
}