{
  "$ref": "http://core.espnuk.org/v2/sports/cricket/athletes/1326486",
  "id": "1326486",
  "guid": "2d28e792-1b27-3c87-a269-c994deceaf01",
  "uid": "s:200~a:1326486",
  "type": "cricket",
  "name": "Jarryd Allan",
  "firstName": "Jarryd",
  "middleName": "",
  "lastName": "Allan",
  "shortName": "Allan",
  "fullName": "Jarryd David Allan",
  "displayName": "Jarryd Allan",
  "weight": 0,
  "height": 0.0,
  "age": 35,
  "dateOfBirthStr": "1990-11-18T00:00Z",
  "dateOfBirth": "1990-11-18T00:00Z",
  "dateOfDeathStr": "",
  "dateOfDeath": "",
  "isActive": true,
  "active": true,
  "gender": "M",
  "debutYear": null,
  "birthPlace": {},
  "jersey": null,
  "style": [
    {
      "description": "Right-hand bat",
      "shortDescription": "Rhb",
      "type": "batting"
    }
  ],
  "styles": [
    {
      "description": "Right-hand bat",
      "shortDescription": "Rhb",
      "type": "batting"
    }
  ],
  "position": {
    "$ref": "http://core.espnuk.org/v2/sports/cricket/positions/UKN",
    "id": "UKN",
    "name": "Unknown",
    "abbreviation": "UKN",
    "leaf": true,
    "parent": {
      "$ref": "http://core.espnuk.org/v2/sports/cricket/positions/UKN"
    }
  },
  "battingName": "JD Allan",
  "fieldingName": "Allan",
  "country": 165,
  "relations": [],
  "majorTeams": [
    {
      "$ref": "http://core.espnuk.org/v2/sports/cricket/teams/165"
    }
  ],
  "headshot": {
    "href": "https://a.espncdn.com/i/headshots/cricket/players/default-player-logo-500.png",
    "rel": [
      "full",
      "default"
    ]
  },
  "flag": {
    "href": "https://a.espncdn.com/i/teamlogos/cricket/500/165.png",
    "width": 500,
    "height": 500,
    "alt": "VAN",
    "rel": [
      "full",
      "default"
    ]
  },
  "team": {
    "$ref": "http://core.espnuk.org/v2/sports/cricket/teams/165"
  },
  "news": {
    "$ref": "http://core.espnuk.org/v2/sports/cricket/athletes/1326486/news"
  },
  "debuts": [
    {
      "$ref": "http://core.espnuk.org/v2/sports/cricket/leagues/1333912/events/1333918"
    },
    {
      "$ref": "http://core.espnuk.org/v2/sports/cricket/leagues/1333913/events/1333918"
    },
    {
      "$ref": "http://core.espnuk.org/v2/sports/cricket/leagues/1326333/events/1326339"
    },
    {
      "$ref": "http://core.espnuk.org/v2/sports/cricket/leagues/1326335/events/1326339"
    },
    {
      "$ref": "http://core.espnuk.org/v2/sports/cricket/leagues/1200432/events/1326339"
    },
    {
      "$ref": "http://core.espnuk.org/v2/sports/cricket/leagues/1333912/events/1333918"
    },
    {
      "$ref": "http://core.espnuk.org/v2/sports/cricket/leagues/1333913/events/1333918"
    }
  ],
  "links": [
    {
      "language": "en",
      "rel": [
        "playercard",
        "desktop"
      ],
      "href": "https://www.espncricinfo.com/ci/content/player/1326486.html",
      "text": "Player Card",
      "shortText": "Player Card",
      "isExternal": false,
      "isPremium": false
    }
  ]
}