{
  "$ref": "http://core.espnuk.org/v2/sports/cricket/athletes/1387417",
  "id": "1387417",
  "guid": "8ec1f039-d074-3565-9306-c1d39e1cea8d",
  "uid": "s:200~a:1387417",
  "type": "cricket",
  "name": "Kaung Htet Kyaw",
  "firstName": "Kaung",
  "middleName": "",
  "lastName": "Kyaw",
  "shortName": "",
  "fullName": "Kaung Htet Kyaw",
  "displayName": "Kaung Htet Kyaw",
  "weight": 0,
  "height": 0,
  "age": 24,
  "dateOfBirthStr": "2002-04-11T00:00Z",
  "dateOfBirth": "2002-04-11T00:00Z",
  "dateOfDeathStr": "",
  "dateOfDeath": "",
  "isActive": true,
  "active": true,
  "gender": "M",
  "debutYear": null,
  "birthPlace": {},
  "jersey": null,
  "style": [
    {
      "description": "Right-hand bat",
      "shortDescription": "Rhb",
      "type": "batting"
    },
    {
      "description": "Right-arm medium-fast",
      "shortDescription": "Rmf",
      "type": "bowling"
    }
  ],
  "styles": [
    {
      "description": "Right-hand bat",
      "shortDescription": "Rhb",
      "type": "batting"
    },
    {
      "description": "Right-arm medium-fast",
      "shortDescription": "Rmf",
      "type": "bowling"
    }
  ],
  "position": {
    "$ref": "http://core.espnuk.org/v2/sports/cricket/positions/UKN",
    "id": "UKN",
    "name": "Unknown",
    "abbreviation": "UKN",
    "leaf": true,
    "parent": {
      "$ref": "http://core.espnuk.org/v2/sports/cricket/positions/UKN"
    }
  },
  "battingName": "Kaung Htet Kyaw",
  "fieldingName": "Kaung Htet Kyaw",
  "country": 1116403,
  "relations": [],
  "majorTeams": [
    {
      "$ref": "http://core.espnuk.org/v2/sports/cricket/teams/1116403"
    }
  ],
  "headshot": {
    "href": "https://a.espncdn.com/i/headshots/cricket/players/default-player-logo-500.png",
    "rel": [
      "full",
      "default"
    ]
  },
  "flag": {
    "href": "https://a.espncdn.com/i/teamlogos/cricket/500/1116403.png",
    "width": 500,
    "height": 500,
    "alt": "MYAN",
    "rel": [
      "full",
      "default"
    ]
  },
  "team": {
    "$ref": "http://core.espnuk.org/v2/sports/cricket/teams/1116403"
  },
  "news": {
    "$ref": "http://core.espnuk.org/v2/sports/cricket/athletes/1387417/news"
  },
  "debuts": [
    {
      "$ref": "http://core.espnuk.org/v2/sports/cricket/leagues/1508260/events/1508271"
    },
    {
      "$ref": "http://core.espnuk.org/v2/sports/cricket/leagues/1508262/events/1508271"
    },
    {
      "$ref": "http://core.espnuk.org/v2/sports/cricket/leagues/1508263/events/1508271"
    },
    {
      "$ref": "http://core.espnuk.org/v2/sports/cricket/leagues/1508260/events/1508271"
    },
    {
      "$ref": "http://core.espnuk.org/v2/sports/cricket/leagues/1508262/events/1508271"
    },
    {
      "$ref": "http://core.espnuk.org/v2/sports/cricket/leagues/1508263/events/1508271"
    }
  ],
  "links": [
    {
      "language": "en",
      "rel": [
        "playercard",
        "desktop"
      ],
      "href": "https://www.espncricinfo.com/ci/content/player/1387417.html",
      "text": "Player Card",
      "shortText": "Player Card",
      "isExternal": false,
      "isPremium": false
    }
  ]
}