{
  "$ref": "http://core.espnuk.org/v2/sports/cricket/athletes/1402419",
  "id": "1402419",
  "guid": "d26343e3-3f5c-3d15-afeb-c9efe4f2048e",
  "uid": "s:200~a:1402419",
  "type": "cricket",
  "name": "Paras Singh",
  "firstName": "Paras",
  "middleName": "",
  "lastName": "Singh",
  "shortName": "Paras Singh",
  "fullName": "Benny Paras Singh",
  "displayName": "Paras Singh",
  "weight": 0,
  "height": 0.0,
  "age": 33,
  "dateOfBirthStr": "1992-11-30T00:00Z",
  "dateOfBirth": "1992-11-30T00:00Z",
  "dateOfDeathStr": "",
  "dateOfDeath": "",
  "isActive": true,
  "active": true,
  "gender": "M",
  "debutYear": null,
  "birthPlace": {},
  "jersey": null,
  "style": [
    {
      "description": "Right-hand bat",
      "shortDescription": "Rhb",
      "type": "batting"
    },
    {
      "description": "Right-arm medium",
      "shortDescription": "Rm",
      "type": "bowling"
    }
  ],
  "styles": [
    {
      "description": "Right-hand bat",
      "shortDescription": "Rhb",
      "type": "batting"
    },
    {
      "description": "Right-arm medium",
      "shortDescription": "Rm",
      "type": "bowling"
    }
  ],
  "position": {
    "$ref": "http://core.espnuk.org/v2/sports/cricket/positions/UKN",
    "id": "UKN",
    "name": "Unknown",
    "abbreviation": "UKN",
    "leaf": true,
    "parent": {
      "$ref": "http://core.espnuk.org/v2/sports/cricket/positions/UKN"
    }
  },
  "battingName": "Paras Singh",
  "fieldingName": "Paras Singh",
  "country": 19,
  "relations": [],
  "majorTeams": [
    {
      "$ref": "http://core.espnuk.org/v2/sports/cricket/teams/1256754"
    }
  ],
  "headshot": {
    "href": "https://a.espncdn.com/i/headshots/cricket/players/default-player-logo-500.png",
    "rel": [
      "full",
      "default"
    ]
  },
  "flag": {
    "href": "https://a.espncdn.com/i/teamlogos/cricket/500/19.png",
    "width": 500,
    "height": 500,
    "alt": "HKG",
    "rel": [
      "full",
      "default"
    ]
  },
  "team": {
    "$ref": "http://core.espnuk.org/v2/sports/cricket/teams/19"
  },
  "news": {
    "$ref": "http://core.espnuk.org/v2/sports/cricket/athletes/1402419/news"
  },
  "debuts": [
    {
      "$ref": "http://core.espnuk.org/v2/sports/cricket/leagues/1494079/events/1494098"
    },
    {
      "$ref": "http://core.espnuk.org/v2/sports/cricket/leagues/1494080/events/1494098"
    },
    {
      "$ref": "http://core.espnuk.org/v2/sports/cricket/leagues/1494077/events/1494098"
    },
    {
      "$ref": "http://core.espnuk.org/v2/sports/cricket/leagues/1494077/events/1494098"
    },
    {
      "$ref": "http://core.espnuk.org/v2/sports/cricket/leagues/1494079/events/1494098"
    },
    {
      "$ref": "http://core.espnuk.org/v2/sports/cricket/leagues/1494080/events/1494098"
    }
  ],
  "links": [
    {
      "language": "en",
      "rel": [
        "playercard",
        "desktop"
      ],
      "href": "https://www.espncricinfo.com/ci/content/player/1402419.html",
      "text": "Player Card",
      "shortText": "Player Card",
      "isExternal": false,
      "isPremium": false
    }
  ]
}