{
  "$ref": "http://core.espnuk.org/v2/sports/cricket/athletes/14306",
  "id": "14306",
  "guid": "150fa3ad-69af-df51-e14b-16b12499df6e",
  "uid": "s:200~a:14306",
  "type": "cricket",
  "name": "Joe Humphries",
  "firstName": "Joe",
  "middleName": "",
  "lastName": "Humphries",
  "shortName": "Humphries",
  "fullName": "Joseph Humphries",
  "displayName": "Joe Humphries",
  "weight": 0,
  "height": 0,
  "age": 69,
  "dateOfBirthStr": "1876-05-19T00:00Z",
  "dateOfBirth": "1876-05-19T00:00Z",
  "dateOfDeathStr": "1946-05-07T00:00Z",
  "dateOfDeath": "1946-05-07T00:00Z",
  "isActive": false,
  "active": false,
  "gender": "M",
  "debutYear": null,
  "birthPlace": {},
  "jersey": null,
  "style": [
    {
      "description": "Right-hand bat",
      "shortDescription": "Rhb",
      "type": "batting"
    }
  ],
  "styles": [
    {
      "description": "Right-hand bat",
      "shortDescription": "Rhb",
      "type": "batting"
    }
  ],
  "position": {
    "$ref": "http://core.espnuk.org/v2/sports/cricket/positions/UKN",
    "id": "UKN",
    "name": "Unknown",
    "abbreviation": "UKN",
    "leaf": true,
    "parent": {
      "$ref": "http://core.espnuk.org/v2/sports/cricket/positions/UKN"
    }
  },
  "battingName": "J Humphries",
  "fieldingName": "Humphries",
  "country": 1,
  "relations": [],
  "majorTeams": [
    {
      "$ref": "http://core.espnuk.org/v2/sports/cricket/teams/1"
    },
    {
      "$ref": "http://core.espnuk.org/v2/sports/cricket/teams/904"
    }
  ],
  "headshot": {
    "href": "https://a.espncdn.com/i/headshots/cricket/players/default-player-logo-500.png",
    "rel": [
      "full",
      "default"
    ]
  },
  "flag": {
    "href": "https://a.espncdn.com/i/teamlogos/cricket/500/1.png",
    "width": 500,
    "height": 500,
    "alt": "ENG",
    "rel": [
      "full",
      "default"
    ]
  },
  "team": {
    "$ref": "http://core.espnuk.org/v2/sports/cricket/teams/1"
  },
  "news": {
    "$ref": "http://core.espnuk.org/v2/sports/cricket/athletes/14306/news"
  },
  "debuts": [
    {
      "$ref": "http://core.espnuk.org/v2/sports/cricket/leagues/60291/events/62492"
    },
    {
      "$ref": "http://core.espnuk.org/v2/sports/cricket/leagues/61717/events/62492"
    }
  ],
  "links": [
    {
      "language": "en",
      "rel": [
        "playercard",
        "desktop"
      ],
      "href": "https://www.espncricinfo.com/ci/content/player/14306.html",
      "text": "Player Card",
      "shortText": "Player Card",
      "isExternal": false,
      "isPremium": false
    }
  ]
}