{
  "$ref": "http://core.espnuk.org/v2/sports/cricket/athletes/1542290",
  "id": "1542290",
  "guid": "93d6f7b7-fecd-30ec-bfba-d3e0ef83e6b2",
  "uid": "s:200~a:1542290",
  "type": "cricket",
  "name": "Aarkin Kessar",
  "firstName": "Aarkin",
  "middleName": "",
  "lastName": "Kessar",
  "shortName": "Kessar",
  "fullName": "Aarkin Kessar",
  "displayName": "Aarkin Kessar",
  "weight": 0,
  "height": 0.0,
  "age": 18,
  "dateOfBirthStr": "2007-11-04T00:00Z",
  "dateOfBirth": "2007-11-04T00:00Z",
  "dateOfDeathStr": "",
  "dateOfDeath": "",
  "isActive": true,
  "active": true,
  "gender": "M",
  "debutYear": null,
  "birthPlace": {},
  "jersey": null,
  "style": [
    {
      "description": "Right-hand bat",
      "shortDescription": "Rhb",
      "type": "batting"
    },
    {
      "description": "Right-arm medium",
      "shortDescription": "Rm",
      "type": "bowling"
    }
  ],
  "styles": [
    {
      "description": "Right-hand bat",
      "shortDescription": "Rhb",
      "type": "batting"
    },
    {
      "description": "Right-arm medium",
      "shortDescription": "Rm",
      "type": "bowling"
    }
  ],
  "position": {
    "$ref": "http://core.espnuk.org/v2/sports/cricket/positions/UKN",
    "id": "UKN",
    "name": "Unknown",
    "abbreviation": "UKN",
    "leaf": true,
    "parent": {
      "$ref": "http://core.espnuk.org/v2/sports/cricket/positions/UKN"
    }
  },
  "battingName": "A Kessar",
  "fieldingName": "Kessar",
  "country": 23,
  "relations": [],
  "majorTeams": [
    {
      "$ref": "http://core.espnuk.org/v2/sports/cricket/teams/23"
    }
  ],
  "headshot": {
    "href": "https://a.espncdn.com/i/headshots/cricket/players/default-player-logo-500.png",
    "rel": [
      "full",
      "default"
    ]
  },
  "flag": {
    "href": "https://a.espncdn.com/i/teamlogos/cricket/500/23.png",
    "width": 500,
    "height": 500,
    "alt": "SGP",
    "rel": [
      "full",
      "default"
    ]
  },
  "team": {
    "$ref": "http://core.espnuk.org/v2/sports/cricket/teams/23"
  },
  "news": {
    "$ref": "http://core.espnuk.org/v2/sports/cricket/athletes/1542290/news"
  },
  "debuts": [
    {
      "$ref": "http://core.espnuk.org/v2/sports/cricket/leagues/1541797/events/1541804"
    },
    {
      "$ref": "http://core.espnuk.org/v2/sports/cricket/leagues/1541801/events/1541804"
    },
    {
      "$ref": "http://core.espnuk.org/v2/sports/cricket/leagues/1541797/events/1541804"
    },
    {
      "$ref": "http://core.espnuk.org/v2/sports/cricket/leagues/1541801/events/1541804"
    }
  ],
  "links": [
    {
      "language": "en",
      "rel": [
        "playercard",
        "desktop"
      ],
      "href": "https://www.espncricinfo.com/ci/content/player/1542290.html",
      "text": "Player Card",
      "shortText": "Player Card",
      "isExternal": false,
      "isPremium": false
    }
  ]
}