{
  "$ref": "http://core.espnuk.org/v2/sports/cricket/athletes/17125",
  "id": "17125",
  "guid": "008ad1ac-d904-c692-c818-49dffc29e923",
  "uid": "s:200~a:17125",
  "type": "cricket",
  "name": "Tim Munton",
  "firstName": "Tim",
  "middleName": "",
  "lastName": "Munton",
  "shortName": "Munton",
  "fullName": "Timothy Alan Munton",
  "displayName": "Tim Munton",
  "weight": 0,
  "height": 0,
  "age": 60,
  "dateOfBirthStr": "1965-07-30T00:00Z",
  "dateOfBirth": "1965-07-30T00:00Z",
  "dateOfDeathStr": "",
  "dateOfDeath": "",
  "isActive": false,
  "active": false,
  "gender": "M",
  "debutYear": null,
  "birthPlace": {},
  "jersey": null,
  "style": [
    {
      "description": "Right-hand bat",
      "shortDescription": "Rhb",
      "type": "batting"
    },
    {
      "description": "Right-arm medium-fast",
      "shortDescription": "Rmf",
      "type": "bowling"
    }
  ],
  "styles": [
    {
      "description": "Right-hand bat",
      "shortDescription": "Rhb",
      "type": "batting"
    },
    {
      "description": "Right-arm medium-fast",
      "shortDescription": "Rmf",
      "type": "bowling"
    }
  ],
  "position": {
    "$ref": "http://core.espnuk.org/v2/sports/cricket/positions/UKN",
    "id": "UKN",
    "name": "Unknown",
    "abbreviation": "UKN",
    "leaf": true,
    "parent": {
      "$ref": "http://core.espnuk.org/v2/sports/cricket/positions/UKN"
    }
  },
  "battingName": "TA Munton",
  "fieldingName": "Munton",
  "country": 1,
  "relations": [],
  "majorTeams": [
    {
      "$ref": "http://core.espnuk.org/v2/sports/cricket/teams/1"
    },
    {
      "$ref": "http://core.espnuk.org/v2/sports/cricket/teams/904"
    },
    {
      "$ref": "http://core.espnuk.org/v2/sports/cricket/teams/1428"
    }
  ],
  "headshot": {
    "href": "https://a.espncdn.com/i/headshots/cricket/players/default-player-logo-500.png",
    "rel": [
      "full",
      "default"
    ]
  },
  "flag": {
    "href": "https://a.espncdn.com/i/teamlogos/cricket/500/1.png",
    "width": 500,
    "height": 500,
    "alt": "ENG",
    "rel": [
      "full",
      "default"
    ]
  },
  "team": {
    "$ref": "http://core.espnuk.org/v2/sports/cricket/teams/1"
  },
  "news": {
    "$ref": "http://core.espnuk.org/v2/sports/cricket/athletes/17125/news"
  },
  "debuts": [
    {
      "$ref": "http://core.espnuk.org/v2/sports/cricket/leagues/60581/events/63577"
    },
    {
      "$ref": "http://core.espnuk.org/v2/sports/cricket/leagues/61462/events/63577"
    }
  ],
  "links": [
    {
      "language": "en",
      "rel": [
        "playercard",
        "desktop"
      ],
      "href": "https://www.espncricinfo.com/ci/content/player/17125.html",
      "text": "Player Card",
      "shortText": "Player Card",
      "isExternal": false,
      "isPremium": false
    }
  ]
}