{
  "$ref": "http://core.espnuk.org/v2/sports/cricket/athletes/308794",
  "id": "308794",
  "guid": "d6939ab0-3f1c-3ea5-9037-64388549cff0",
  "uid": "s:200~a:308794",
  "type": "cricket",
  "name": "Michael Swart",
  "firstName": "Michael",
  "middleName": "",
  "lastName": "Swart",
  "shortName": "Swart",
  "fullName": "Michael Richard Swart",
  "displayName": "Michael Swart",
  "weight": 0,
  "height": 0.0,
  "age": 43,
  "dateOfBirthStr": "1982-10-01T00:00Z",
  "dateOfBirth": "1982-10-01T00:00Z",
  "dateOfDeathStr": "",
  "dateOfDeath": "",
  "isActive": true,
  "active": true,
  "gender": "M",
  "debutYear": null,
  "birthPlace": {},
  "jersey": null,
  "style": [
    {
      "description": "Right-hand bat",
      "shortDescription": "Rhb",
      "type": "batting"
    },
    {
      "description": "Right-arm offbreak",
      "shortDescription": "Ob",
      "type": "bowling"
    }
  ],
  "styles": [
    {
      "description": "Right-hand bat",
      "shortDescription": "Rhb",
      "type": "batting"
    },
    {
      "description": "Right-arm offbreak",
      "shortDescription": "Ob",
      "type": "bowling"
    }
  ],
  "position": {
    "$ref": "http://core.espnuk.org/v2/sports/cricket/positions/MBT",
    "id": "MBT",
    "name": "Middle-order batter",
    "abbreviation": "MBT",
    "leaf": true,
    "parent": {
      "$ref": "http://core.espnuk.org/v2/sports/cricket/positions/MBT"
    }
  },
  "battingName": "MR Swart",
  "fieldingName": "Swart",
  "country": 2,
  "relations": [],
  "majorTeams": [
    {
      "$ref": "http://core.espnuk.org/v2/sports/cricket/teams/15"
    },
    {
      "$ref": "http://core.espnuk.org/v2/sports/cricket/teams/308790"
    },
    {
      "$ref": "http://core.espnuk.org/v2/sports/cricket/teams/602"
    },
    {
      "$ref": "http://core.espnuk.org/v2/sports/cricket/teams/625"
    },
    {
      "$ref": "http://core.espnuk.org/v2/sports/cricket/teams/626"
    }
  ],
  "headshot": {
    "href": "https://a.espncdn.com/i/headshots/cricket/players/full/308794.png",
    "rel": [
      "full",
      "default"
    ]
  },
  "flag": {
    "href": "https://a.espncdn.com/i/teamlogos/cricket/500/2.png",
    "width": 500,
    "height": 500,
    "alt": "AUS",
    "rel": [
      "full",
      "default"
    ]
  },
  "team": {
    "$ref": "http://core.espnuk.org/v2/sports/cricket/teams/2"
  },
  "news": {
    "$ref": "http://core.espnuk.org/v2/sports/cricket/athletes/308794/news"
  },
  "debuts": [
    {
      "$ref": "http://core.espnuk.org/v2/sports/cricket/leagues/492583/events/504778"
    },
    {
      "$ref": "http://core.espnuk.org/v2/sports/cricket/leagues/518430/events/504778"
    },
    {
      "$ref": "http://core.espnuk.org/v2/sports/cricket/leagues/532912/events/546410"
    },
    {
      "$ref": "http://core.espnuk.org/v2/sports/cricket/leagues/546488/events/546410"
    },
    {
      "$ref": "http://core.espnuk.org/v2/sports/cricket/leagues/546490/events/546410"
    },
    {
      "$ref": "http://core.espnuk.org/v2/sports/cricket/leagues/411985/events/417661"
    },
    {
      "$ref": "http://core.espnuk.org/v2/sports/cricket/leagues/411990/events/417692"
    },
    {
      "$ref": "http://core.espnuk.org/v2/sports/cricket/leagues/461027/events/461028"
    }
  ],
  "links": [
    {
      "language": "en",
      "rel": [
        "playercard",
        "desktop"
      ],
      "href": "https://www.espncricinfo.com/ci/content/player/308794.html",
      "text": "Player Card",
      "shortText": "Player Card",
      "isExternal": false,
      "isPremium": false
    }
  ]
}