{
  "$ref": "http://core.espnuk.org/v2/sports/cricket/athletes/32231",
  "id": "32231",
  "guid": "64ce281b-cffa-02bf-a9bb-e278328fed81",
  "uid": "s:200~a:32231",
  "type": "cricket",
  "name": "Brijesh Patel",
  "firstName": "Brijesh",
  "middleName": "",
  "lastName": "Patel",
  "shortName": "Patel",
  "fullName": "Brijesh Pursuram Patel",
  "displayName": "Brijesh Patel",
  "weight": 0,
  "height": 0.0,
  "age": 73,
  "dateOfBirthStr": "1952-11-24T00:00Z",
  "dateOfBirth": "1952-11-24T00:00Z",
  "dateOfDeathStr": "",
  "dateOfDeath": "",
  "isActive": false,
  "active": false,
  "gender": "M",
  "debutYear": null,
  "birthPlace": {},
  "jersey": null,
  "style": [
    {
      "description": "Right-hand bat",
      "shortDescription": "Rhb",
      "type": "batting"
    },
    {
      "description": "Right-arm offbreak",
      "shortDescription": "Ob",
      "type": "bowling"
    }
  ],
  "styles": [
    {
      "description": "Right-hand bat",
      "shortDescription": "Rhb",
      "type": "batting"
    },
    {
      "description": "Right-arm offbreak",
      "shortDescription": "Ob",
      "type": "bowling"
    }
  ],
  "position": {
    "$ref": "http://core.espnuk.org/v2/sports/cricket/positions/MBT",
    "id": "MBT",
    "name": "Middle-order batter",
    "abbreviation": "MBT",
    "leaf": true,
    "parent": {
      "$ref": "http://core.espnuk.org/v2/sports/cricket/positions/MBT"
    }
  },
  "battingName": "BP Patel",
  "fieldingName": "Patel",
  "country": 6,
  "relations": [
    {
      "athlete": {
        "$ref": "http://core.espnuk.org/v2/sports/cricket/athletes/32805"
      },
      "relation": "Uncle"
    },
    {
      "athlete": {
        "$ref": "http://core.espnuk.org/v2/sports/cricket/athletes/32778"
      },
      "relation": "Uncle"
    },
    {
      "athlete": {
        "$ref": "http://core.espnuk.org/v2/sports/cricket/athletes/32812"
      },
      "relation": "Uncle"
    },
    {
      "athlete": {
        "$ref": "http://core.espnuk.org/v2/sports/cricket/athletes/32388"
      },
      "relation": "Son"
    }
  ],
  "majorTeams": [
    {
      "$ref": "http://core.espnuk.org/v2/sports/cricket/teams/6"
    },
    {
      "$ref": "http://core.espnuk.org/v2/sports/cricket/teams/1872"
    },
    {
      "$ref": "http://core.espnuk.org/v2/sports/cricket/teams/1872"
    },
    {
      "$ref": "http://core.espnuk.org/v2/sports/cricket/teams/2600"
    }
  ],
  "headshot": {
    "href": "https://a.espncdn.com/i/headshots/cricket/players/default-player-logo-500.png",
    "rel": [
      "full",
      "default"
    ]
  },
  "flag": {
    "href": "https://a.espncdn.com/i/teamlogos/cricket/500/6.png",
    "width": 500,
    "height": 500,
    "alt": "IND",
    "rel": [
      "full",
      "default"
    ]
  },
  "team": {
    "$ref": "http://core.espnuk.org/v2/sports/cricket/teams/6"
  },
  "news": {
    "$ref": "http://core.espnuk.org/v2/sports/cricket/athletes/32231/news"
  },
  "debuts": [
    {
      "$ref": "http://core.espnuk.org/v2/sports/cricket/leagues/62274/events/63125"
    },
    {
      "$ref": "http://core.espnuk.org/v2/sports/cricket/leagues/60450/events/63125"
    },
    {
      "$ref": "http://core.espnuk.org/v2/sports/cricket/leagues/62274/events/64951"
    },
    {
      "$ref": "http://core.espnuk.org/v2/sports/cricket/leagues/60789/events/64951"
    }
  ],
  "links": [
    {
      "language": "en",
      "rel": [
        "playercard",
        "desktop"
      ],
      "href": "https://www.espncricinfo.com/ci/content/player/32231.html",
      "text": "Player Card",
      "shortText": "Player Card",
      "isExternal": false,
      "isPremium": false
    }
  ]
}