{
  "$ref": "http://core.espnuk.org/v2/sports/cricket/athletes/52801",
  "id": "52801",
  "guid": "08283878-31bd-17c6-3b38-a197135a074d",
  "uid": "s:200~a:52801",
  "type": "cricket",
  "name": "Allan Rae",
  "firstName": "Allan",
  "middleName": "",
  "lastName": "Rae",
  "shortName": "Rae",
  "fullName": "Allan Fitzroy Rae",
  "displayName": "Allan Rae",
  "weight": 0,
  "height": 0.0,
  "age": 82,
  "dateOfBirthStr": "1922-09-30T00:00Z",
  "dateOfBirth": "1922-09-30T00:00Z",
  "dateOfDeathStr": "2005-02-27T00:00Z",
  "dateOfDeath": "2005-02-27T00:00Z",
  "isActive": false,
  "active": false,
  "gender": "M",
  "debutYear": null,
  "birthPlace": {},
  "jersey": null,
  "style": [
    {
      "description": "Left-hand bat",
      "shortDescription": "Lhb",
      "type": "batting"
    }
  ],
  "styles": [
    {
      "description": "Left-hand bat",
      "shortDescription": "Lhb",
      "type": "batting"
    }
  ],
  "position": {
    "$ref": "http://core.espnuk.org/v2/sports/cricket/positions/UKN",
    "id": "UKN",
    "name": "Unknown",
    "abbreviation": "UKN",
    "leaf": true,
    "parent": {
      "$ref": "http://core.espnuk.org/v2/sports/cricket/positions/UKN"
    }
  },
  "battingName": "AF Rae",
  "fieldingName": "Rae",
  "country": 4,
  "relations": [
    {
      "athlete": {
        "$ref": "http://core.espnuk.org/v2/sports/cricket/athletes/52835"
      },
      "relation": "Father"
    }
  ],
  "majorTeams": [
    {
      "$ref": "http://core.espnuk.org/v2/sports/cricket/teams/4"
    },
    {
      "$ref": "http://core.espnuk.org/v2/sports/cricket/teams/3751"
    }
  ],
  "headshot": {
    "href": "https://a.espncdn.com/i/headshots/cricket/players/default-player-logo-500.png",
    "rel": [
      "full",
      "default"
    ]
  },
  "flag": {
    "href": "https://a.espncdn.com/i/teamlogos/cricket/500/4.png",
    "width": 500,
    "height": 500,
    "alt": "WI",
    "rel": [
      "full",
      "default"
    ]
  },
  "team": {
    "$ref": "http://core.espnuk.org/v2/sports/cricket/teams/4"
  },
  "news": {
    "$ref": "http://core.espnuk.org/v2/sports/cricket/athletes/52801/news"
  },
  "debuts": [
    {
      "$ref": "http://core.espnuk.org/v2/sports/cricket/leagues/60343/events/62690"
    },
    {
      "$ref": "http://core.espnuk.org/v2/sports/cricket/leagues/61938/events/62690"
    }
  ],
  "links": [
    {
      "language": "en",
      "rel": [
        "playercard",
        "desktop"
      ],
      "href": "https://www.espncricinfo.com/ci/content/player/52801.html",
      "text": "Player Card",
      "shortText": "Player Card",
      "isExternal": false,
      "isPremium": false
    }
  ]
}