{
  "$ref": "http://core.espnuk.org/v2/sports/cricket/athletes/55560",
  "id": "55560",
  "guid": "cf058de2-2e4e-a776-6856-b9e5180dec12",
  "uid": "s:200~a:55560",
  "type": "cricket",
  "name": "Charlie Lock",
  "firstName": "Charlie",
  "middleName": "",
  "lastName": "Lock",
  "shortName": "Lock",
  "fullName": "Alan Charles Ingram Lock",
  "displayName": "Charlie Lock",
  "weight": 0,
  "height": 0,
  "age": 63,
  "dateOfBirthStr": "1962-09-10T00:00Z",
  "dateOfBirth": "1962-09-10T00:00Z",
  "dateOfDeathStr": "",
  "dateOfDeath": "",
  "isActive": false,
  "active": false,
  "gender": "M",
  "debutYear": null,
  "birthPlace": {},
  "jersey": null,
  "style": [
    {
      "description": "Right-hand bat",
      "shortDescription": "Rhb",
      "type": "batting"
    },
    {
      "description": "Right-arm fast-medium",
      "shortDescription": "Rfm",
      "type": "bowling"
    }
  ],
  "styles": [
    {
      "description": "Right-hand bat",
      "shortDescription": "Rhb",
      "type": "batting"
    },
    {
      "description": "Right-arm fast-medium",
      "shortDescription": "Rfm",
      "type": "bowling"
    }
  ],
  "position": {
    "$ref": "http://core.espnuk.org/v2/sports/cricket/positions/BL",
    "id": "BL",
    "name": "Bowler",
    "abbreviation": "BL",
    "leaf": true,
    "parent": {
      "$ref": "http://core.espnuk.org/v2/sports/cricket/positions/BL"
    }
  },
  "battingName": "ACI Lock",
  "fieldingName": "Lock",
  "country": 9,
  "relations": [],
  "majorTeams": [
    {
      "$ref": "http://core.espnuk.org/v2/sports/cricket/teams/9"
    },
    {
      "$ref": "http://core.espnuk.org/v2/sports/cricket/teams/3830"
    },
    {
      "$ref": "http://core.espnuk.org/v2/sports/cricket/teams/3845"
    }
  ],
  "headshot": {
    "href": "https://a.espncdn.com/i/headshots/cricket/players/default-player-logo-500.png",
    "rel": [
      "full",
      "default"
    ]
  },
  "flag": {
    "href": "https://a.espncdn.com/i/teamlogos/cricket/500/9.png",
    "width": 500,
    "height": 500,
    "alt": "ZIM",
    "rel": [
      "full",
      "default"
    ]
  },
  "team": {
    "$ref": "http://core.espnuk.org/v2/sports/cricket/teams/9"
  },
  "news": {
    "$ref": "http://core.espnuk.org/v2/sports/cricket/athletes/55560/news"
  },
  "debuts": [
    {
      "$ref": "http://core.espnuk.org/v2/sports/cricket/leagues/60622/events/63693"
    },
    {
      "$ref": "http://core.espnuk.org/v2/sports/cricket/leagues/61835/events/63693"
    },
    {
      "$ref": "http://core.espnuk.org/v2/sports/cricket/leagues/60980/events/64519"
    },
    {
      "$ref": "http://core.espnuk.org/v2/sports/cricket/leagues/62002/events/64519"
    }
  ],
  "links": [
    {
      "language": "en",
      "rel": [
        "playercard",
        "desktop"
      ],
      "href": "https://www.espncricinfo.com/ci/content/player/55560.html",
      "text": "Player Card",
      "shortText": "Player Card",
      "isExternal": false,
      "isPremium": false
    }
  ]
}