{
  "$ref": "http://core.espnuk.org/v2/sports/cricket/athletes/56094",
  "id": "56094",
  "guid": "62a373e7-f01f-804e-b820-badc6652aa00",
  "uid": "s:200~a:56094",
  "type": "cricket",
  "name": "Saiful Islam",
  "firstName": "Saiful",
  "middleName": "",
  "lastName": "Islam",
  "shortName": "",
  "fullName": "Mohammad Saiful Islam Khan",
  "displayName": "Saiful Islam",
  "weight": 0,
  "height": 0,
  "age": 57,
  "dateOfBirthStr": "1969-04-14T00:00Z",
  "dateOfBirth": "1969-04-14T00:00Z",
  "dateOfDeathStr": "",
  "dateOfDeath": "",
  "isActive": true,
  "active": true,
  "gender": "M",
  "debutYear": null,
  "birthPlace": {},
  "jersey": null,
  "style": [
    {
      "description": "Right-hand bat",
      "shortDescription": "Rhb",
      "type": "batting"
    },
    {
      "description": "Right-arm medium",
      "shortDescription": "Rm",
      "type": "bowling"
    }
  ],
  "styles": [
    {
      "description": "Right-hand bat",
      "shortDescription": "Rhb",
      "type": "batting"
    },
    {
      "description": "Right-arm medium",
      "shortDescription": "Rm",
      "type": "bowling"
    }
  ],
  "position": {
    "$ref": "http://core.espnuk.org/v2/sports/cricket/positions/UKN",
    "id": "UKN",
    "name": "Unknown",
    "abbreviation": "UKN",
    "leaf": true,
    "parent": {
      "$ref": "http://core.espnuk.org/v2/sports/cricket/positions/UKN"
    }
  },
  "battingName": "Saiful Islam",
  "fieldingName": "Saiful Islam",
  "country": 25,
  "relations": [],
  "majorTeams": [
    {
      "$ref": "http://core.espnuk.org/v2/sports/cricket/teams/25"
    },
    {
      "$ref": "http://core.espnuk.org/v2/sports/cricket/teams/682"
    }
  ],
  "headshot": {
    "href": "https://a.espncdn.com/i/headshots/cricket/players/default-player-logo-500.png",
    "rel": [
      "full",
      "default"
    ]
  },
  "flag": {
    "href": "https://a.espncdn.com/i/teamlogos/cricket/500/25.png",
    "width": 500,
    "height": 500,
    "alt": "BAN",
    "rel": [
      "full",
      "default"
    ]
  },
  "team": {
    "$ref": "http://core.espnuk.org/v2/sports/cricket/teams/25"
  },
  "news": {
    "$ref": "http://core.espnuk.org/v2/sports/cricket/athletes/56094/news"
  },
  "debuts": [
    {
      "$ref": "http://core.espnuk.org/v2/sports/cricket/leagues/60913/events/65683"
    },
    {
      "$ref": "http://core.espnuk.org/v2/sports/cricket/leagues/61645/events/65683"
    },
    {
      "$ref": "http://core.espnuk.org/v2/sports/cricket/leagues/62194/events/65683"
    }
  ],
  "links": [
    {
      "language": "en",
      "rel": [
        "playercard",
        "desktop"
      ],
      "href": "https://www.espncricinfo.com/ci/content/player/56094.html",
      "text": "Player Card",
      "shortText": "Player Card",
      "isExternal": false,
      "isPremium": false
    }
  ]
}