{
  "$ref": "http://core.espnuk.org/v2/sports/cricket/athletes/859431",
  "id": "859431",
  "guid": "fa2200b2-5fdb-2d00-4d7f-4f578f1ed0f0",
  "uid": "s:200~a:859431",
  "type": "cricket",
  "name": "Harsheed Chohan",
  "firstName": "Harsheed",
  "middleName": "",
  "lastName": "Chohan",
  "shortName": "Chohan",
  "fullName": "Harsheed Anantkumar Chohan",
  "displayName": "Harsheed Chohan",
  "weight": 0,
  "height": 0.0,
  "age": 28,
  "dateOfBirthStr": "1998-06-27T00:00Z",
  "dateOfBirth": "1998-06-27T00:00Z",
  "dateOfDeathStr": "",
  "dateOfDeath": "",
  "isActive": true,
  "active": true,
  "gender": "M",
  "debutYear": null,
  "birthPlace": {},
  "jersey": null,
  "style": [
    {
      "description": "Right-hand bat",
      "shortDescription": "Rhb",
      "type": "batting"
    },
    {
      "description": "Right-arm medium",
      "shortDescription": "Rm",
      "type": "bowling"
    }
  ],
  "styles": [
    {
      "description": "Right-hand bat",
      "shortDescription": "Rhb",
      "type": "batting"
    },
    {
      "description": "Right-arm medium",
      "shortDescription": "Rm",
      "type": "bowling"
    }
  ],
  "position": {
    "$ref": "http://core.espnuk.org/v2/sports/cricket/positions/UKN",
    "id": "UKN",
    "name": "Unknown",
    "abbreviation": "UKN",
    "leaf": true,
    "parent": {
      "$ref": "http://core.espnuk.org/v2/sports/cricket/positions/UKN"
    }
  },
  "battingName": "HA Chohan",
  "fieldingName": "Chohan",
  "country": 160,
  "relations": [],
  "majorTeams": [
    {
      "$ref": "http://core.espnuk.org/v2/sports/cricket/teams/160"
    }
  ],
  "headshot": {
    "href": "https://a.espncdn.com/i/headshots/cricket/players/default-player-logo-500.png",
    "rel": [
      "full",
      "default"
    ]
  },
  "flag": {
    "href": "https://a.espncdn.com/i/teamlogos/cricket/500/160.png",
    "width": 500,
    "height": 500,
    "alt": "TAN",
    "rel": [
      "full",
      "default"
    ]
  },
  "team": {
    "$ref": "http://core.espnuk.org/v2/sports/cricket/teams/160"
  },
  "news": {
    "$ref": "http://core.espnuk.org/v2/sports/cricket/athletes/859431/news"
  },
  "debuts": [
    {
      "$ref": "http://core.espnuk.org/v2/sports/cricket/leagues/1283018/events/1283043"
    },
    {
      "$ref": "http://core.espnuk.org/v2/sports/cricket/leagues/1283591/events/1283043"
    },
    {
      "$ref": "http://core.espnuk.org/v2/sports/cricket/leagues/1283017/events/1283043"
    },
    {
      "$ref": "http://core.espnuk.org/v2/sports/cricket/leagues/1451884/events/1451896"
    },
    {
      "$ref": "http://core.espnuk.org/v2/sports/cricket/leagues/1451892/events/1451896"
    },
    {
      "$ref": "http://core.espnuk.org/v2/sports/cricket/leagues/1283017/events/1283043"
    },
    {
      "$ref": "http://core.espnuk.org/v2/sports/cricket/leagues/1283018/events/1283043"
    },
    {
      "$ref": "http://core.espnuk.org/v2/sports/cricket/leagues/1283591/events/1283043"
    }
  ],
  "links": [
    {
      "language": "en",
      "rel": [
        "playercard",
        "desktop"
      ],
      "href": "https://www.espncricinfo.com/ci/content/player/859431.html",
      "text": "Player Card",
      "shortText": "Player Card",
      "isExternal": false,
      "isPremium": false
    }
  ]
}