{
  "$ref": "http://core.espnuk.org/v2/sports/cricket/teams/441434",
  "id": "441434",
  "uid": "s:200~t:441434",
  "location": "England",
  "name": "Northamptonshire Under-15s",
  "nickname": "Northamptonshire Under-15s",
  "abbreviation": "",
  "displayName": "Northamptonshire Under-15s",
  "shortDisplayName": "",
  "isNational": false,
  "isActive": true,
  "countryCode": "www",
  "slug": "northamptonshire-under-15s",
  "classes": [],
  "color": "",
  "logos": [],
  "athletes": {
    "$ref": "http://core.espnuk.org/v2/sports/cricket/teams/441434/athletes"
  },
  "links": [
    {
      "language": "en",
      "rel": [
        "clubhouse",
        "desktop"
      ],
      "href": "https://www.espn.in/cricket/team/_/id/441434/northamptonshire-under-15s",
      "text": "Clubhouse",
      "shortText": "Clubhouse",
      "isExternal": false,
      "isPremium": false
    },
    {
      "language": "en",
      "rel": [
        "fixtures",
        "desktop"
      ],
      "href": "https://www.espn.in/cricket/scores/team/441434/northamptonshire-under-15s",
      "text": "Fixtures",
      "shortText": "Fixtures",
      "isExternal": false,
      "isPremium": false
    }
  ]
}